[
	{
		"class": "SCHOOL_KID",
		"name": "TED",
		"party": [
			{
				"species": "SPECIES_RALTS",
				"level": 47,
				"iv": 10
			}
		]
	},
	{
		"class": "SCHOOL_KID",
		"name": "PAUL",
		"party": [
			{
				"species": "SPECIES_NUMEL",
				"level": 45,
				"iv": 10
			},
			{
				"species": "SPECIES_ODDISH",
				"level": 45,
				"iv": 10
			},
			{
				"species": "SPECIES_WINGULL",
				"level": 45,
				"iv": 10
			}
		]
	},
	{
		"class": "SCHOOL_KID",
		"music": "GIRL",
		"female": true,
		"name": "GEORGIA",
		"party": [
			{
				"species": "SPECIES_SHROOMISH",
				"level": 44,
				"iv": 10
			},
			{
				"species": "SPECIES_BEAUTIFLY",
				"level": 44,
				"iv": 10
			}
		]
	}
]